{
"type": "FeatureCollection",
"crs": { "type": "name", "properties": { "name": "urn:ogc:def:crs:OGC:1.3:CRS84" } },
"features": [
{ "type": "Feature", "properties": { "projektnr": 5601030014, "dato": "2016-06-13", "tid": "12:08", "maaler": "ART", "klasse": "KF7", "typegenfind": "U121", "origin_text": "1604109_234.x34", "origin_date": "2016-06-13T10:57:48.0Z", "Rotation": 87.502 }, "geometry": { "type": "Point", "coordinates": [ 8.316272264562819, 56.038664992353354, 2.335 ] } },
{ "type": "Feature", "properties": { "projektnr": 5601030014, "dato": "2016-06-13", "tid": "12:08", "maaler": "ART", "klasse": "KF7", "typegenfind": "U121", "origin_text": "1604109_234.x34", "origin_date": "2016-06-13T10:57:48.0Z", "Rotation": 82.709 }, "geometry": { "type": "Point", "coordinates": [ 8.316564435373428, 56.039813454571473, 2.002 ] } },
{ "type": "Feature", "properties": { "projektnr": 5601030014, "dato": "2016-06-13", "tid": "12:08", "maaler": "ART", "klasse": "KF7", "typegenfind": "U121", "origin_text": "1604109_234.x34", "origin_date": "2016-06-13T10:57:48.0Z", "Rotation": 79.043 }, "geometry": { "type": "Point", "coordinates": [ 8.305412559302075, 56.060702262918184, 1.713 ] } },
{ "type": "Feature", "properties": { "projektnr": 5601030014, "dato": "2016-06-13", "tid": "12:08", "maaler": "ART", "klasse": "KF7", "typegenfind": "U121", "origin_text": "1604109_234.x34", "origin_date": "2016-06-13T10:57:48.0Z", "Rotation": 84.736 }, "geometry": { "type": "Point", "coordinates": [ 8.30689661622014, 56.065233237079269, 4.906 ] } },
{ "type": "Feature", "properties": { "projektnr": 5601030014, "dato": "2016-06-13", "tid": "12:08", "maaler": "ART", "klasse": "KF7", "typegenfind": "U121", "origin_text": "1604109_234.x34", "origin_date": "2016-06-13T10:57:48.0Z", "Rotation": -131.111 }, "geometry": { "type": "Point", "coordinates": [ 8.315311237885755, 56.059997052159794, 5.228 ] } },
{ "type": "Feature", "properties": { "projektnr": 5601030014, "dato": "2016-06-13", "tid": "12:08", "maaler": "ART", "klasse": "KF7", "typegenfind": "U121", "origin_text": "1604109_234.x34", "origin_date": "2016-06-13T10:57:48.0Z", "Rotation": -177.604 }, "geometry": { "type": "Point", "coordinates": [ 8.313455395320823, 56.059394535654476, 3.081 ] } },
{ "type": "Feature", "properties": { "projektnr": 5601030014, "dato": "2016-06-13", "tid": "12:08", "maaler": "ART", "klasse": "KF7", "typegenfind": "U121", "origin_text": "1604109_234.x34", "origin_date": "2016-06-13T10:57:48.0Z", "Rotation": -107.464 }, "geometry": { "type": "Point", "coordinates": [ 8.312899904902757, 56.059382468520184, 3.077 ] } },
{ "type": "Feature", "properties": { "projektnr": 5601030014, "dato": "2016-06-13", "tid": "12:08", "maaler": "ART", "klasse": "KF7", "typegenfind": "U121", "origin_text": "1604109_234.x34", "origin_date": "2016-06-13T10:57:48.0Z", "Rotation": 163.527 }, "geometry": { "type": "Point", "coordinates": [ 8.312794358919053, 56.059363865801735, 2.949 ] } },
{ "type": "Feature", "properties": { "projektnr": 5601030014, "dato": "2016-06-13", "tid": "12:08", "maaler": "ART", "klasse": "KF7", "typegenfind": "U121", "origin_text": "1604109_234.x34", "origin_date": "2016-06-13T10:57:48.0Z", "Rotation": -72.48 }, "geometry": { "type": "Point", "coordinates": [ 8.313599930433803, 56.059072468920519, 3.659 ] } },
{ "type": "Feature", "properties": { "projektnr": 5601030014, "dato": "2016-06-13", "tid": "12:08", "maaler": "ART", "klasse": "KF7", "typegenfind": "U121", "origin_text": "1604109_234.x34", "origin_date": "2016-06-13T10:57:48.0Z", "Rotation": 85.66 }, "geometry": { "type": "Point", "coordinates": [ 8.315816289803447, 56.062722929673598, 8.412 ] } },
{ "type": "Feature", "properties": { "projektnr": 5601030014, "dato": "2016-06-13", "tid": "12:08", "maaler": "ART", "klasse": "KF7", "typegenfind": "U121", "origin_text": "1604109_234.x34", "origin_date": "2016-06-13T10:57:48.0Z", "Rotation": 97.851 }, "geometry": { "type": "Point", "coordinates": [ 8.311595607032441, 56.017028292144147, 1.457 ] } },
{ "type": "Feature", "properties": { "projektnr": 5601030014, "dato": "2016-06-13", "tid": "12:08", "maaler": "ART", "klasse": "KF7", "typegenfind": "U121", "origin_text": "1604109_234.x34", "origin_date": "2016-06-13T10:57:48.0Z", "Rotation": 76.633 }, "geometry": { "type": "Point", "coordinates": [ 8.312317745505865, 56.020665325486156, 1.62 ] } }
]
}
